luma_diagnostics/__init__.py
luma_diagnostics/__main__.py
luma_diagnostics/api_tests.py
luma_diagnostics/case_manager.py
luma_diagnostics/cli.py
luma_diagnostics/diagnostics.py
luma_diagnostics/file_utils.py
luma_diagnostics/generation_tests.py
luma_diagnostics/messages.py
luma_diagnostics/mock_tests.py
luma_diagnostics/post_install.py
luma_diagnostics/settings.py
luma_diagnostics/system_info.py
luma_diagnostics/tests.py
luma_diagnostics/utils.py
luma_diagnostics/wizard.py
luma_diagnostics-1.0.2.dist-info/LICENSE
luma_diagnostics-1.0.2.dist-info/METADATA
luma_diagnostics-1.0.2.dist-info/WHEEL
luma_diagnostics-1.0.2.dist-info/entry_points.txt
luma_diagnostics-1.0.2.dist-info/top_level.txt
luma_diagnostics-1.0.2.dist-info/RECORD
