Metadata-Version: 2.2
Name: luma-diagnostics
Version: 1.0.2
Summary: An unofficial diagnostic tool for troubleshooting LUMA Dream Machine API issues
Home-page: https://github.com/caseyfenton/luma-diagnostics
Author: Casey Fenton
Author-email: casey@caseyfenton.com
Project-URL: Bug Tracker, https://github.com/caseyfenton/luma-diagnostics/issues
Classifier: Development Status :: 4 - Beta
Classifier: Intended Audience :: Developers
Classifier: License :: OSI Approved :: MIT License
Classifier: Operating System :: OS Independent
Classifier: Programming Language :: Python :: 3
Classifier: Programming Language :: Python :: 3.8
Classifier: Programming Language :: Python :: 3.9
Classifier: Programming Language :: Python :: 3.10
Classifier: Programming Language :: Python :: 3.11
Requires-Python: >=3.8
License-File: LICENSE
Requires-Dist: requests>=2.25.1
Requires-Dist: python-dotenv>=0.19.0
Requires-Dist: pillow>=8.3.1
Requires-Dist: dnspython>=2.1.0
Requires-Dist: certifi>=2021.5.30
Requires-Dist: questionary>=1.10.0
Requires-Dist: rich>=10.6.0
Requires-Dist: psutil>=5.8.0
Provides-Extra: test
Requires-Dist: pytest>=7.0.0; extra == "test"
Requires-Dist: pytest-cov>=4.0.0; extra == "test"
Requires-Dist: pillow>=8.3.1; extra == "test"
Requires-Dist: numpy>=1.21.0; extra == "test"
Dynamic: author
Dynamic: author-email
Dynamic: classifier
Dynamic: description
Dynamic: description-content-type
Dynamic: home-page
Dynamic: project-url
Dynamic: provides-extra
Dynamic: requires-dist
Dynamic: requires-python
Dynamic: summary
